Metadata-Version: 2.1
Name: ethans-first-upload
Version: 0.2
Summary: Gaussian and Binomial distributions
Home-page: UNKNOWN
Author-email: ethanblake417@gmail.com
License: UNKNOWN
Platform: UNKNOWN
